garrus/__init__.py
garrus/calibrations/__init__.py
garrus/calibrations/binning/__init__.py
garrus/calibrations/scaling/__init__.py
garrus/calibrations/scaling/platt.py
garrus/const.py
garrus/core/__init__.py
garrus/core/calibration.py
garrus/core/metric.py
garrus/core/visualization.py
garrus/metrics/__init__.py
garrus/metrics/aupre.py
garrus/metrics/aurc.py
garrus/metrics/brier.py
garrus/metrics/eaurc.py
garrus/metrics/ece.py
garrus/metrics/fpr_n_tpr.py
garrus/metrics/nll.py
garrus/visualizations/__init__.py
garrus/visualizations/confidence_histogram.py
garrus/visualizations/reliability_diagram.py
garrus-0.3.0.dist-info/LICENSE
garrus-0.3.0.dist-info/METADATA
garrus-0.3.0.dist-info/WHEEL
garrus-0.3.0.dist-info/RECORD
