Metadata-Version: 2.1
Name: garrus
Version: 0.3.0
Summary: A Python package for machine learning and data visualization
Home-page: https://github.com/sleep3r/garrus
License: MIT
Keywords: machine-learning,data-visualization,pytorch
Author: sleep3r
Author-email: sleep3r@icloud.com
Requires-Python: >=3.12,<4.0
Classifier: Development Status :: 4 - Beta
Classifier: Intended Audience :: Developers
Classifier: License :: OSI Approved :: MIT License
Classifier: Programming Language :: Python :: 3
Classifier: Programming Language :: Python :: 3.12
Requires-Dist: numpy (>=1.26.4,<2.0.0)
Requires-Dist: plotly (>=5.24.0,<6.0.0)
Requires-Dist: scikit-learn (>=1.6.0,<2.0.0)
Requires-Dist: torch (>=2.5.1,<3.0.0)
Requires-Dist: tqdm (>=4.66.5,<5.0.0)
Project-URL: Repository, https://github.com/sleep3r/garrus
